mcp_monkdb/__init__.py
mcp_monkdb/env_vals.py
mcp_monkdb/main.py
mcp_monkdb/mcp_server.py
mcp_monkdb/models.py
mcp_monkdb/otel_setup.py
mcp_monkdb-0.2.1.dist-info/METADATA
mcp_monkdb-0.2.1.dist-info/WHEEL
mcp_monkdb-0.2.1.dist-info/entry_points.txt
mcp_monkdb-0.2.1.dist-info/RECORD
