Metadata-Version: 2.4
Name: mcp-monkdb
Version: 0.2.1
Summary: An MCP server for MonkDB
Project-URL: Home, https://github.com/monkdbofficial/monkdb-mcp
Author-email: MonkDB Developers <devs@monkdb.com>
License-Expression: Apache-2.0
Requires-Python: >=3.13
Requires-Dist: mcp[cli]>=1.3.0
Requires-Dist: monkdb>=1.0.5
Requires-Dist: pip-system-certs>=4.0
Requires-Dist: python-dotenv>=1.0.1
Requires-Dist: uvicorn>=0.34.0
